{
    "SKIP": "Παράλειψη",
    "ME": "Εγώ",
    "LASTSEEN": "Τελευταία ένδειξη",
    "HISTORY": "Ιστορικό",
    "ARCHIVE": "Αρχειοθέτηση",
    "ARCHIVED": "Αρχειοθετήθηκε",
    "CAMPAIGNS": "Καμπάνιες",
    "CAMPAIGN": "Καμπάνια",
    "NEWCAMPAIGN": "Νέα καμπάνια",
    "COMBO": "Μοναδική επιλογή",
    "SELECT": "Μοναδική επιλογή",
    "COMBOMULTI": "Πολλαπλή επιλογή",
    "COMBOBUTTONS": "Μοναδική επιλογή κουμπιού",
    "COMBOMULTIBUTTONS": "Πολλαπλή επιλογή κουμπιών",
    "SHORTTEXT": "Σύντομο κείμενο",
    "TEXT": "Κείμενο",
    "LONGTEXT": "Εκτενές κείμενο",
    "TEXTAREA": "Εκτενές κείμενο",
    "DATE": "Ημερομηνία",
    "CREATIONDATE": "Ημερομηνία δημιουργίας",
    "TIME": "Ώρα",
    "NUMBER": "Αριθμός",
    "BARCODE": "Γραμμικός κώδικας",
    "CHECKBOX": "Πλαίσιο επιλογής",
    "TOOGLE": "Εναλλαγή",
    "TEL": "Αριθμός τηλεφώνου",
    "STARRATING": "Αστέρια κατάταξης",
    "ADD": "Προσθήκη",
    "NEW": "Νέο",
    "CREATE": "Δημιουργία",
    "COPY": "Αντιγραφή",
    "LOAD": "Φόρτωση",
    "BACKGROUND": "Φόντο",
    "ALLOWCOMMENTS": "Σχόλια",
    "ALLOWTIME": "Καταγραφή ώρας",
    "OTHER1": "Άλλο",
    "OTHER": "Άλλο (προσδιορίστε)",
    "SAVING": "Αποθήκευση σε εξέλιξη",
    "RETRY": "Επανάληψη προσπάθειας",
    "DATA": "Δεδομένα",
    "PIE": "Γράφημα πίτας",
    "BAR": "Ράβδος",
    "COLUMN": "Στήλη",
    "LINE": "Γραμμή",
    "BYDATE": "Με ημερομηνία",
    "BYVALIDITY": "Με συμβατότητα",
    "INFORMATION": "Πληροφορίες",
    "ROLES": "Ρόλοι",
    "SUPPORT": "Υποστήριξη",
    "CODE": "Κωδικός",
    "VALUE": "Τιμή",
    "ADMIN": "Διαχειριστής",
    "TEAM": "Ομάδα",
    "PROGRESS": "Πρόοδος",
    "VALIDATION": "Επικύρωση",
    "TAGS": "Ετικέτες",
    "FIELDS": "Πεδία",
    "FIELD": "Πεδίο",
    "WHATSNEW": "Τι νέο υπάρχει;",
    "ALLOWLIBRARY": "Να επιτρέπεται εισαγωγή βιβλιοθήκης",
    "ALLOWANNOTATE": "Να επιτρέπονται σχόλια",
    "ALLOWHISTORY": "Να επιτρέπεται ιστορικό",
    "SHOWONLOCATION": "Εμφάνιση σε τοποθεσία",
    "ANNOTATE": "Δημιουργία σχολίου",
    "INSTRUCTIONS": "Οδηγίες",
    "SUBMIT": "Υποβολή",
    "REFERENCE": "Αναφορά",
    "VERSION": "Έκδοση ",
    "RATE": "Αξιολόγηση",
    "SIGNATURE": "Υπογραφή",
    "OFFLINEMODE": "Δεν υπάρχει σύνδεση στο internet",
    "RANGE": "Ρυθμιστικό",
    "NOTIFICATIONEMAILS": "Εmail(s) ειδοποίησης",
    "SKIPVALIDATION": "Συμβατό από προεπιλογή",
    "HIDEMOBILE": "Απόκρυψη από κινητό",
    "SHOWSERVICE": "Εμφάνιση υπηρεσίας",
    "VALIDATEDBY": "Επικυρώθηκε από",
    "INFO": "Πληροφορίες",
    "SCORING": "Σκορ",
    "FACTOR": "Παράγοντας",
    "OFFLINE": "εκτός σύνδεσης",
    "DEVICE": "Συσκευή",
    "PLATFORM": "Πλατφόρμα",
    "CATEGORY": "Κατηγορία",
    "CATEGORIES": "Κατηγορίες",
    "FILTERS": "Φίλτρα",
    "SERVICE": "Αίτημα",
    "AUTOCOMPLETE": "Αυτόματη ολοκλήρωση",
    "STEP": "Βήμα",
    "SERVICES": "Αιτήματα",
    "CATALOG": "Κατάλογος",
    "SELECTPRODUCT": "Επιλέξτε ένα προϊόν",
    "LEGEND": "Υπόμνημα",
    "ADDPRODUCT": "Προσθήκη προϊόντος",
    "ADDPRODUCTTOBASKET": "Προσθήκη προϊόντος(-ων)",
    "SCANPRODUCTTOBASKET": "Σάρωση προϊόντος(-ων)",
    "PRODUCT": "Προϊόν",
    "PRODUCTS": "Προϊόντα",
    "BASKET": "Καλάθι",
    "SERVICESAVEDSUCCESS": "Το αίτημά σας αποθηκεύτηκε με επιτυχία. Θα επικοινωνήσουμε μαζί σας το συντομότερο δυνατό.",
    "ON": "Πάνω",
    "CONDITION": "Προϋπόθεση",
    "CALENDAR": "Ημερολόγιο",
    "EVENT": "Συμβάν",
    "NOTES": "Σημειώσεις",
    "VERSIONMIN": "Έκδοση ελάχ.",
    "LATEST": "Τελευταία",
    "OPERATOR": "Χειριστής",
    "PAGES": "Σελίδες",
    "PAGE": "Σελίδα",
    "CONDITIONS": "Προϋποθέσες",
    "CONTAINS": "Περιέχει",
    "TODO": "Σχέδιο δράσης",
    "SELECTUSER": "Επιλέξτε χρήστη",
    "SELECTUSERS": "Επιλέξτε χρήστες",
    "TASKS": "Εργασίες",
    "TASK": "Εργασία",
    "DUEDATE": "Ημερομηνία παράδοσης",
    "DELETETODOTASKCONFIRM": "Θέλετε σίγουρα να διαγράψετε αυτήν την εργασία;",
    "ENVIRONMENT": "Περιβάλλον",
    "EMAILREPORT": "Αποστολή αναφοράς μέσω Email",
    "EMAILREPORTSEND": "Στείλατε {{count}} email(s)",
    "SENDANEWPHOTO": "αποστολή νέας φωτογραφίας",
    "REQUESTOR": "Αιτών",
    "PRIORITY": "Προτεραιότητα",
    "VALIDFROM": "Ισχύει από",
    "VALIDUNTIL": "Ισχύει έως",
    "FROM": "Από",
    "UNTIL": "Έως",
    "VALIDITY": "Εγκυρότητα",
    "CHANNEL": "Κανάλι",
    "QUESTION": "Ερώτηση",
    "ANSWER": "Απάντηση",
    "APPLY": "Εφαρμογή",
    "READMORE": "Εμφάνιση περισσότερων",
    "ASK": "Ερώτηση",
    "SHOWANSWERS": "Εμφάνιση απαντήσεων",
    "SCORE": "Σκορ",
    "EXPLANATION": "Επεξήγηση",
    "RANKING": "Κατάταξη",
    "ACTIVITY": "Δραστηριότητα",
    "SUBMITTEXT": "Υποβολή κειμένου",
    "SUCCESSTEXT": "Κείμενο επιτυχίας",
    "SERVICEUPDATED": "Το αίτημά σας ενημερώθηκε",
    "MISSIONVALIDATED": "Η αποστολή σας είναι συμβατή",
    "MISSIONREJECTED": "Η αποστολή σας δεν είναι συμβατή",
    "MISSIONANNOTATED": "Η αποστολή σας σχολιάστηκε",
    "SHOWUSERSEMAIL": "Εμφάνιση στους χρήστες κουμπιού email",
    "SENDFINISHEDEMAIL": "Λήψη email σε ολοκληρωμένη αποστολή ",
    "PHOTOLIVECOUNTER": "Εντοπισμός εικόνας",
    "COLOR": "Χρώμα",
    "WALKTHROUGH1": "Επίδειξη",
    "VIEWPHOTO": "Εμφάνιση φωτογραφίας",
    "DELETEPHOTO": "Διαγραφή φωτογραφίας",
    "DELETEPHOTOSINALBUM": "Να μην αποθηκευτούν φωτογραφίες σε άλμπουμ",
    "OVERVIEW": "Επισκόπηση",
    "CHECK": "Έλεγχος",
    "CHECKAVAILABLE": "Έλεγχος διαθέσιμης αποστολής @τοποθεσία",
    "CHECKEXISTING": "Έλεγχος υπάρχουσας αποστολής @τοποθεσία",
    "PROCESSING": "Επεξεργασία",
    "COMPONENTS": "Συστατικά",
    "WELCOME": "Καλωσήρθατε στις λειτουργίες του YOOBIC",
    "LOGIN": "Σύνδεση",
    "SIGNUP": "Εγγραφή",
    "SIGNIN": "Είσοδος",
    "FORGOTPASSWORD": "Ξεχάσατε τον κωδικό πρόσβασης;",
    "EMAILPLACEHOLDER": "Ποιο είναι το email σας;",
    "PASSWORDPLACEHOLDER": "Δημιουργήστε κωδικό πρόσβασης",
    "PASSWORD": "Κωδικός πρόσβασης",
    "TERMSANDCONDITION": "Όροι & Προϋποθέσεις",
    "BOOK": "Φόρτωση",
    "EMAILREQUIRED": "Απαιτείται έγκυρη διεύθυνση email",
    "PASSWORDREQUIRED": "Απαιτείται έγκυρος κωδικός πρόσβασης",
    "PASSWORDTOOSHORT": "Απαιτούνται τουλάχιστον 6 χαρακτήρες",
    "HOME": "Επιλογή αποστολής",
    "LEVEL": "Επίπεδο",
    "SEARCH": "Αναζήτηση",
    "CLEAR": "Απαλοιφή",
    "DETAILS": "Λεπτομέρειες",
    "MISSIONBOOKED": "Αποστολή σε εξέλιξη",
    "CONGRATULATIONS": "Συγχαρητήρια",
    "CURRENT": "Τρέχουσες",
    "FINISHED": "Ολοκληρώθηκαν",
    "WHEN": "Πότε",
    "BOOKED": "Σε εξέλιξη",
    "NONE": "κανένας\/καμία",
    "SAVE": "Αποθήκευση",
    "SAVENOTVALID": "Βεβαιωθείτε ότι όλα τα υποχρεωτικά πεδία (*) είναι συμπληρωμένα πρώτα",
    "SAVECONFIRM": "Θέλετε σίγουρα να υποβάλλετε τις απαντήσεις σας;",
    "SAVECONFIRMPROFILE": "Θέλετε σίγουρα να αποθηκεύσετε το προφίλ σας;",
    "SAVECONFIRMSERVICE": "Θέλετε σίγουρα να υποβάλλετε αυτό το αίτημα;",
    "SAVECONFIRMCALENDAR": "Θέλετε σίγουρα να σχεδιάσετε την εργασία;",
    "FORMS": "Φόρμες",
    "ADDAPHOTO": "Κάντε κλικ για να προσθέσετε φωτογραφία",
    "CHANGEPHOTO": "Κάντε κλικ στη φωτογραφία για να την αλλάξετε...",
    "RESETPASSWORD": "Επαναφορά κωδικού πρόσβασης",
    "RESETPASSWORDDESCRIPTION": "Θα αποσταλεί νέος κωδικός πρόσβασης. Ελέγξτε το φάκελο εισερχομένων...",
    "RESETPASSWORDOK": "Ο νέος κωδικός πρόσβασης στάλθηκε. Ελέγξτε το φάκελο εισερχομένων...",
    "RESETPASSWORDERROR": "Δεν βρέθηκε κανένας χρήστης με τη σχετική διεύθυνση email.",
    "PERSONALINFO": "Προσωπικές πληροφορίες",
    "EMAIL": "Email",
    "EMAILS": "Emails",
    "FIRSTNAME": "Όνομα",
    "LASTNAME": "Επώνυμο",
    "CREDITCARD": "Πληροφορίες πληρωμής",
    "PASSWORDDONOTMATCH": "Οι κωδικοί πρόσβασης δεν ταιριάζουν",
    "CHANGEPASSWORD": "Αλλαγή κωδικού πρόσβασης",
    "CHANGEPASSWORDOK": "Ο κωδικός πρόσβασης άλλαξε με επιτυχία.",
    "CHANGEPASSWORDERROR": "Παρουσιάστηκε σφάλμα κατά την αλλαγή του κωδικού πρόσβασης.",
    "PASSWORDIDENTICAL": "Οι κωδικοί πρόσβασης είναι ίδιοι",
    "OLDPASSWORD": "Παλιός κωδικός πρόσβασης",
    "NEWPASSWORD": "Νέος κωδικός πρόσβασης",
    "CONFIRMPASSWORD": "Επιβεβαίωση νέου κωδικού πρόσβασης",
    "INVALID_PASSWORD": "Ο κωδικός πρόσβασης που ορίστηκε δεν είναι σωστός",
    "DISTANCE": "Απόσταση",
    "NEXT": "Επόμενο",
    "MISSIONBOOKVERSION": "Για πρόσβαση σε αυτήν την αποστολή πρέπει να κάνετε ενημέρωση στην πιο πρόσφατη έκδοση από το app store\/play store",
    "UNBOOK": "Κατάργηση κράτησης",
    "UNBOOKCONFIRM": "Θέλετε σίγουρα να απορρίψετε αυτήν την αποστολή; Οι προ-αποθηκευμένες απαντήσεις θα χαθούν.",
    "START": "Έναρξη",
    "AUDIO": "Ήχος",
    "LOGOUT": "Έξοδος",
    "LOGOUTCONFIRM": "Θέλετε σίγουρα έξοδο από την εφαρμογή;",
    "PULLTOREFRESH": "Σύρετε για ανανέωση...",
    "CURRENCY": "£",
    "DISTANCEUNIT": "m",
    "SETTINGS": "Ρυθμίσεις",
    "CANCEL": "Ακύρωση",
    "OK": "OK",
    "ADDRESS": "Διεύθυνση",
    "CANCELMISSIONFORM": "Έξοδος",
    "CANCELMISSIONFORMCONFIRM": "Θέλετε σίγουρα να αφήσετε αυτήν την αποστολή; Τα δεδομένα θα αποθηκευτούν και θα μπορείτε να επιστρέψετε οποιαδήποτε στιγμή για επεξεργασία πριν υποβάλλετε την αποστολή. ",
    "FEEDEMPTY": "Φαίνεται ότι δεν υπάρχουν νέα για εμφάνιση για την ώρα",
    "LISTEMPTY": "Φαίνεται ότι δεν υπάρχει τίποτα για εμφάνιση για την ώρα",
    "CALENDAREMPTY": "Φαίνεται ότι δεν έχετε προγραμματίσει κάτι",
    "END": "Τέλος",
    "YES": "Ναι",
    "NO": "Όχι",
    "RADIUS": "Ακτίνα σε μίλια",
    "CHAT": "Συνομιλία",
    "CALL": "Κλήση",
    "VALIDATED": "Συμβατό",
    "REJECTED": "Μη συμβατό",
    "POLL": "Ψηφοφορία",
    "POLLS": "Ψηφοφορίες",
    "BACK": "Επιστροφή",
    "PAYMENTS": "Πληρωμές",
    "SHOW": "Εμφάνιση",
    "REQUESTERROR": "Ουπς, φαίνεται ότι δεν μπορέσαμε να ανακτήσουμε τίποτα. Ελέγξτε τη σύνδεσή σας στο internet.",
    "MISSIONSAVEDSUCCESS": "Η αποστολή αποθηκεύτηκε με επιτυχία",
    "POLLSAVEDSUCCESS": "Η ψηφοφορία αποθηκεύτηκε με επιτυχία",
    "MISSIONSAVEDERROR": "Παρουσιάστηκε σφάλμα κατά την αποθήκευση αυτής της αποστολής. Ελέγξτε τη σύνδεση στο internet και προσπαθήστε ξανά.",
    "QUIZZSAVEDERROR": "Παρουσιάστηκε σφάλμα κατά την αποθήκευση αυτού του κουίζ. Ελέγξτε τη σύνδεση στο internet και προσπαθήστε ξανά.",
    "HELP": "Βοήθεια",
    "DASHBOARD": "Πίνακας εργαλείων",
    "MISSIONS": "Αποστολές",
    "MISSION": "Αποστολή",
    "PHOTO": "Φωτογραφία",
    "IMAGE": "Εικόνα",
    "PHOTOS": "Φωτογραφίες",
    "TITLE": "Τίτλος",
    "PRICE": "Τιμή (€)",
    "REFRESH": "Ανανέωση",
    "LOCATIONS": "Καταστήματα",
    "LOCATION": "Κατάστημα",
    "FILES": "Αρχεία",
    "DOCUMENTS": "Έγγραφα",
    "TYPE": "Τύπος",
    "SIZE": "Μέγεθος",
    "LOCATIONTYPE": "Τύπος καταστήματος",
    "DELETE": "Διαγραφή",
    "UPDATE": "Ενημέρωση",
    "ACTIONS": "Ενέργεια(-ες)",
    "VIEW": "Εμφάνιση",
    "VALIDATE": "Συμβατό",
    "UNVALIDATE": "Μη συμβατό",
    "STATUS": "Κατάσταση",
    "FINISHEDDATE": "Ημερομηνία ολοκλήρωσης",
    "FINISHEDBY": "Ολοκλήρωση έως",
    "DATES": "Ημερομηνίες",
    "USERS": "Χρήστες",
    "USER": "Χρήστης",
    "DESCRIPTION": "Περιγραφή",
    "ICON": "Εικονίδιο",
    "RATING": "Αξιολόγηση",
    "ID": "Αναγνωριστικό",
    "GROUPS": "Ομάδες",
    "PUBLIC": "Δημόσιο",
    "COUNT": "Μέτρηση",
    "SUM": "Σύνολο",
    "AVG": "Μέσος όρος",
    "AVERAGE": "Μέσος όρος",
    "DELETEALL": "Διαγραφή όλων",
    "DELETEALLCONFIRM": "Θέλετε σίγουρα να διαγράψετε {{total}} στοιχεία;",
    "GROUP": "Ομάδα",
    "AVAILABLE": "Διαθέσιμος(-η)",
    "EXPORT": "Εξαγωγή",
    "ACL": "Εξουσιοδοτήσεις",
    "GEOLOC": "Γεωγραφικός προσδιορισμός θέσης",
    "FIRST": "Πρώτο",
    "PREVIOUS": "Προηγούμενο",
    "LAST": "Τελευταίο",
    "finished": "Ολοκληρώθηκε",
    "booked": "Σε εξέλιξη",
    "true": "Ναι",
    "TRUE": "Ναι",
    "false": "Όχι",
    "FALSE": "Όχι",
    "GENERAL": "Γενικό",
    "ANSWERS": "Απάντηση(-εις)",
    "NAME": "Όνομα",
    "UNVALIDATEREASON": "Αιτία μη συμβατότητας",
    "UNVALIDATED": "Μη συμβατό",
    "TOBEVALIDATED": "Προς επικύρωση",
    "MIN": "Ελάχ.",
    "MAX": "Μέγ.",
    "VALUES": "Τιμές",
    "MANDATORY": "Υποχρεωτικό",
    "ORDER": "Σειρά",
    "MAP": "Χάρτης",
    "ADDNEW": "Προσθήκη νέου…",
    "MISSIONTITLE": "Τίτλος αποστολής",
    "MISSIONDESCRIPTION": "Περιγραφή αποστολής",
    "NOTIFY": "Ειδοποίηση",
    "TOTAL": "Σύνολο",
    "NOTIFICATION": "Ειδοποίηση",
    "BODY": "Σώμα",
    "CLASS": "Στυλ",
    "IMPORT": "Εισαγωγή",
    "EXISTING": "Υπάρχον",
    "SEND": "Αποστολή",
    "EDIT": "Επεξεργασία",
    "MISSIONDURATION": "Διάρκεια αποστολής (λεπ.)",
    "DURATION": "Διάρκεια",
    "TODAY": "Σήμερα",
    "TIMESCALE": "Χρονική κλίμακα",
    "LAST7DAYS": "Τελευταίες 7 ημέρες",
    "CONTACT": "Επικοινωνία",
    "STATS": "Στατιστικά",
    "ASSIGNTO": "Εκχώρηση σε",
    "SELECTFILES": "Επιλογή αρχείων",
    "ADDCOMMENT": "Προσθήκη σχολίου",
    "FOLDERS": "Φάκελοι",
    "FOLDER": "Φάκελος",
    "InvalidCredentials": "Μη έγκυρα διαπιστευτήρια, δοκιμάστε ξανά ή κάντε κλικ στο 'Ξεχάσατε τον κωδικό πρόσβασής σας;' για επαναφορά.",
    "UserLockedDown": "Ο λογαριασμός σας κλειδώθηκε ...",
    "AlreadyLoggedIn": "Έχετε ήδη συνδεθεί.",
    "SocialError": "Ουπς, φαίνεται ότι δεν μπορέσαμε να συνδεθούμε μαζί σας μέσω Facebook",
    "UserAlreadyExists": "Αυτό το όνομα χρήστη χρησιμοποιείται ήδη...",
    "UserUnavailable": "Αυτό το όνομα χρήστη χρησιμοποιείται ήδη...",
    "MISSINGCREDENTIALS": "Απαιτείται όνομα χρήστη\/κωδικός πρόσβασης",
    "RequestError": "Ελέγξτε τη σύνδεση στο internet",
    "IncompleteRequestBody": "Έλλειψη δεδομένων",
    "NoAccess": "Λυπούμαστε, δεν έχουμε πρόσβαση σε αυτήν την εφαρμογή",
    "UNKNOWN_ERROR": "Άγνωστο σφάλμα",
    "ERROR": "Σφάλμα",
    "MALE": "Άντρας",
    "FEMALE": "Γυναίκα",
    "STORE": "Κατάστημα",
    "MODEL": "Μοντέλο",
    "YEARS": "έτος(-η)",
    "CONFIRM": "Επιβεβαίωση",
    "CONTRACT": "Συμβόλαιο",
    "CREATED": "Δημιουργήθηκε",
    "watch": "ρολόι",
    "COMMENTS": "Σχόλια",
    "FEED": "Τροφοδοσία ειδήσεων",
    "FEEDS": "Τροφοδοσία ειδήσεων",
    "NEWFEEDPUBLISHED": "Ειδήσεις που δημοσιεύτηκαν",
    "SHARE": "Κοινή χρήση",
    "COMMENT": "Σχόλιο",
    "PROFILEEDIT": "Επεξεργασία προφίλ",
    "BIC": "BIC",
    "LOADING": "Φόρτωση",
    "SMALLPHOTOS": "Μικρές φωτογραφίες",
    "FILTER": "Φίλτρο",
    "LIBRARY": "Βιβλιοθήκη",
    "AGGREGATION": "Συνάθροιση",
    "PREVIEW": "Προεπισκόπηση",
    "EN": "English",
    "FR": "Français",
    "US": "English US",
    "MOBILE": "Κινητό",
    "TEST": "Δοκιμή",
    "LOCATIONVISITED": "Κατάστημα επίσκεψης",
    "AVERAGEMISSIONSPERDAY": "Μέσος αριθμός απόστολών ανά ημέρα",
    "AVERAGEMISSIONSPERUSER": "Μέσος αριθμός απόστολών ανά χρήστη",
    "AREA": "Περιοχή",
    "PALETTE": "Παλέτα ",
    "CHART": "Γράφημα",
    "GRID": "Πλέγμα",
    "DEBUG": "Ενεργοποίηση λειτουργίας εντοπισμού σφαλμάτων",
    "PDF": "Εξαγωγή ως PDF",
    "REJECT": "Μη συμβατό",
    "MODE": "Λειτουργία",
    "SELECTCAMPAIGN": "Επιλογή καμπάνιας",
    "ACTIVE": "Ενεργή",
    "TOTALCOMPLETION": "Σύνολο ολοκλήρωσης",
    "OPTIONS": "Επιλογές",
    "LOCATIONID": "Αναγνωριστικό καταστήματος",
    "LOCATIONTITLE": "Τίτλος καταστήματος",
    "QUERYON": "Προέλευση",
    "GROUPBYDATE": "Ομοδοποίηση με ημερομηνία",
    "DATETIMEFORMAT": "Μορφή ημερομηνίας\/ώρας",
    "GROUPBY": "Ομαδοποίηση με ",
    "SHOWAS": "Εμφάνιση ως",
    "YEAR": "Έτος",
    "QUARTER": "Τρίμηνο",
    "MONTH": "Μήνας",
    "WEEK": "Εβδομάδα",
    "DAY": "Ημέρα",
    "CAMPAIGNTAGS": "Ετικέτες καμπάνιας",
    "LOCATIONTAGS": "Αποθήκευση ετικετών",
    "USERTAGS": "Ετικέτες χρήστη",
    "MESSAGE": "Μήνυμα",
    "ROOT": "Ριζικός κατάλογος",
    "TO": "Προς",
    "CC": "Κοιν.",
    "BCC": "Ιδιαίτ. Κοιν.",
    "REPLY_TO": "Απάντηση σε",
    "SUBJECT": "Θέμα",
    "FOOTER": "Υποσέλιδο",
    "THANKYOU": "Ευχαριστούμε",
    "IN": "Μέσα",
    "EQUALS": "Ίσοι",
    "GREATERTHAN": "Μεγαλύτερο από",
    "LESSTHAN": "Μικρότερο από",
    "LIKE": "Μου αρέσει",
    "EXISTS": "Υπάρχει",
    "VIEWMISSION": "Εμφάνιση αποστολής",
    "VIEWUSER": "Εμφάνιση χρήστη",
    "STATE": "Κατάσταση",
    "COLLAPSE": "Σύμπτυξη",
    "VISIBLE": "Ορατό",
    "INITIALSCORE": "Αρχικό σκορ",
    "MINSCOREFORVALIDATION": "Ελάχιστο σκορ για συμβατότητα",
    "LEADERBOARD": "Πίνακας κατάταξης κορυφαίων",
    "RANK": "Κατάταξη",
    "UNDO": "Αναίρεση",
    "MAXWIDTH": "Μέγ. πλάτος (px)",
    "IMPORTFROMLIBRARY": "Εισαγωγή από βιβλιοθήκη",
    "TRANSLATIONS": "Μεταφράσεις",
    "ES": "Español",
    "NL": "Nederlands",
    "PL": "Polski",
    "DE": "Deutsch",
    "RU": "русский",
    "IT": "Italiano",
    "MISSIONCATEGORY": "Κατηγορία",
    "LIKES": "Επισημάνσεις \"Μου αρέσει\"",
    "SELECTCAMPAIGNS": "Επιλέξτε όλες τις καμπάνιες που θέλετε να δημοσιεύσετε",
    "SELECTCAMPAIGNSMULTI": "Ενεργοποιήστε αυτήν την επιλογή για να δημοσιεύσετε πολλαπλές καμπάνιες μαζί",
    "LIST": "Λίστα",
    "CONTACTS": "Επαφές",
    "NOTE": "Σημείωση",
    "WALKING": "Περπάτημα",
    "CYCLING": "Ποδήλατο",
    "DRIVING": "Οδηγώντας",
    "KPI": "KPI",
    "CUSTOM": "Προσαρμογή",
    "ADVANCED": "Για προχωρημένους",
    "GLOBAL": "Καθολικό",
    "INCLUDETAGS": "Να συμπεριλαμβάνονται ετικέτες τοποθεσίας",
    "INCLUDEDATA": "Να συμπεριλαμβάνονται δεδομένα αποστολής",
    "AGGRIDPAGE": "σελίδα",
    "AGGRIDMORE": "περισσότερα",
    "AGGRIDTO": "σε",
    "AGGRIDOF": "από",
    "AGGRIDNEXT": "Επόμενο",
    "AGGRIDLAST": "Τελευταίο",
    "AGGRIDFIRST": "Πρώτο",
    "AGGRIDPREVIOUS": "Προηγούμενο",
    "AGGRIDLOADINGOOO": "Φόρτωση…",
    "AGGRIDSELECTALL": "Επιλογή όλων",
    "AGGRIDSEARCHOOO": "Αναζήτηση…",
    "AGGRIDBLANKS": "Κενό",
    "AGGRIDFILTEROOO": "Φιλτράρισμα…",
    "AGGRIDAPPLYFILTER": "Εφαρμογή φίλτρου…",
    "AGGRIDEQUALS": "Ίσοι",
    "AGGRIDLESSTHAN": "Μικρότερο από",
    "AGGRIDGREATERTHAN": "Μεγαλύτερο από",
    "AGGRIDCONTAINS": "Περιέχει",
    "AGGRIDSTARTSWITH": "Ξεκινά με ",
    "AGGRIDENDSWITH": "Τελειώνει με",
    "AGGRIDGROUP": "Ομάδα",
    "AGGRIDCOLUMNS": "Στήλες",
    "AGGRIDROWGROUPCOLUMNS": "Στήλες ομάδας",
    "AGGRIDROWGROUPCOLUMNSEMPTYMESSAGE": "Μεταφορά στηλών εδώ για ομαδοποίηση",
    "AGGRIDVALUECOLUMNS": "Στήλες τιμών",
    "AGGRIDPIVOTMODE": "Λειτουργία συγκεντρωτικής προβολής",
    "AGGRIDGROUPS": "Ομάδες",
    "AGGRIDVALUES": "Τιμές",
    "AGGRIDPIVOTS": "Συγκεντρωτικές προβολές",
    "AGGRIDVALUECOLUMNSEMPTYMESSAGE": "Μεταφορά στηλών εδώ για συνάθροιση",
    "AGGRIDPIVOTCOLUMNSEMPTYMESSAGE": "Μεταφορά στηλών εδώ για συγκεντρωτική προβολή",
    "AGGRIDNOROWSTOSHOW": "Δεν υπάρχουν δεδομένα για εμφάνιση",
    "AGGRIDPINCOLUMN": "Καρφίτσωμα αυτής της στήλης",
    "AGGRIDVALUEAGGREGATION": "Τιμή συνάθροισης",
    "AGGRIDAUTOSIZETHISCOLUMN": "Αυτόματη προσαρμογή μεγέθους αυτής της στήλης",
    "AGGRIDAUTOSIZEALLCOLUMNS": "Αυτόματη προσαρμογή μεγέθους όλων των στηλών",
    "AGGRIDGROUPBY": "Ομαδοποίηση με",
    "AGGRIDUNGROUPBY": "Κατάργηση ομαδοποίησης με ",
    "AGGRIDRESETCOLUMNS": "Επαναφορά στηλών",
    "AGGRIDEXPANDALL": "Ανάπτυξη όλων",
    "AGGRIDCOLLAPSEALL": "Σύμπτυξη όλων",
    "AGGRIDTOOLPANEL": "Πίνακας εργαλείων",
    "AGGRIDPINLEFT": "Καρφίτσωμα αριστερά",
    "AGGRIDPINRIGHT": "Καρφίτσωμα δεξιά",
    "AGGRIDNOPIN": "Χωρίς καρφίτσωμα",
    "AGGRIDSUM": "Σύνολο",
    "AGGRIDMIN": "Ελάχ.",
    "AGGRIDMAX": "Μέγ.",
    "AGGRIDNONE": "Κανένα",
    "AGGRIDCOUNT": "Μέτρηση",
    "AGGRIDAVERAGE": "Μέσος όρος",
    "AGGRIDCOPY": "Αντιγραφή",
    "AGGRIDCTRLC": "CTRL + C",
    "AGGRIDPASTE": "Επικόλληση",
    "AGGRIDCTRLV": "CTRL + V",
    "LEVEL1": "Επίπεδο 1",
    "LEVEL2": "Επίπεδο 2",
    "LEVEL3": "Επίπεδο 3",
    "LEVEL4": "Επίπεδο 4",
    "VALIDATIONPROGRESS": "Αναλύθηκε",
    "KPICAMPAIGNSTEMPORALPROGRESS": "Προσωρινή δραστηριότητα",
    "KPICAMPAIGNSLEARNINGCURVE": "Εξέλιξη του ποσοστού συμβατών αποστολών",
    "KPICAMPAIGNSFREQENCYPOS": "Συχνότητα επισκέψεων καταστήματος",
    "KPICAMPAIGNSCORRELATIONPOS": "Συσχέτιση του αριθμού επισκέψεων",
    "_ID": "Αναγνωριστικό",
    "LOCKED": "Κλειδωμένο",
    "SHOWLEVELSLIDER": "Εμφάνιση ρυθμιστικού επιπέδου",
    "SHOWTIMESLIDER": "Εμφάνιση ρυθμιστικού χρόνου",
    "VISITED": "Έγινε επίσκεψη",
    "NOTVISITED": "Δεν έγινε επίσκεψη",
    "CLUSTER": "Συστοιχία",
    "CHARTTYPE": "Τύπος διαγράμματος",
    "DATABASE": "Βάση δεδομένων",
    "MORE": "Περισσότερα",
    "COMPAREDTOLAST7DAYS": "Σε σύγκριση με τις προηγούμενες 7 ημέρες",
    "REASON": "Αιτία",
    "TAG": "Ετικέτα",
    "AROUNDME": "Εμφάνιση καταστημάτων κοντά μου",
    "XAXIS": "Άξονας X",
    "YAXIS": "Άξονας Y ",
    "ACCUMULATOR": "Συσσωρευτής",
    "ONEFOLDERPERSTORE": "Διαίρεση φωτογραφιών με φάκελο ανά κατάστημα",
    "COLUMNS": "Στήλες",
    "TIMER": "Χρονομέτρης",
    "TIMEIN": "Ώρα εισόδου",
    "TIMEOUT": "Ώρα εξόδου",
    "HOURINITIAL": "Ω",
    "MINUTEINITIAL": "Λ",
    "RESET": "Επαναφορά",
    "RESUME": "Συνέχιση",
    "CREATEDBY": "Δημιουργήθηκε από",
    "VIEWS": "Προβολές",
    "PENDING": "Σε εκκρεμότητα",
    "CONTINUE": "Συνέχεια",
    "SAVESERVICELOCALLYCONFIRM": "Δεν ολοκληρώσατε αυτό το αίτημα. Θέλετε να το αποθηκεύσετε τοπικά ώστε να το ολοκληρώσετε αργότερα;",
    "NOTFOUND": "Δεν βρέθηκε",
    "PHOTOSBIG": "Μεγάλες φωτογραφίες",
    "INCLUDEPAGETITLE": "περιλάβετε τίτλο σελίδας",
    "ADDTODO": "Προσθήκη σχεδίου δράσης",
    "PERCENTAGE": "Ποσοστό",
    "REMINDER": "Υπενθύμιση",
    "LINKTOPREVIOUSQUESTION": "Σύνδεσμος σε προηγούμενη ερώτηση",
    "MANDATORYPHOTO": "Απαιτείται φωτογραφία",
    "DATETIME": "Ημερομηνία Ώρα",
    "FORMATDATE": "",
    "FORMATDATEPICKER": "",
    "FORMATDATETIME": "",
    "FORMATDATETIMEPICKER": "",
    "FORMATTIME": "",
    "FORMATTIMEPICKER": "",
    "KEY": "Κλειδί",
    "VALIDATEDDATE": "Ημερομηνία επικύρωσης",
    "AUDIT": "Έλεγχος",
    "PT": "Portuguese",
    "KR": "한국어",
    "JA": "日本語",
    "UA": "Українська",
    "SCHEDULEDDATE": "Προγραμματισμένη ημερομηνία",
    "MISSIONBOOKEDERROR": "Παρουσιάστηκε σφάλμα κατά την κράτηση αυτής της αποστολής. Ελέγξτε τη σύνδεση στο internet και προσπαθήστε ξανά.",
    "DISABLEALLEMAILS": "Απενεργοποίηση όλων των email",
    "DISABLEALLPUSH": "Απενεργοποίηση όλων των ειδοποιήσεων",
    "FINISHEDGROUPS": "Ομάδες για προσθήκη μόλις ολοκληρωθεί η αποστολή",
    "SINGLEFILE": "Μοναδικό αρχείο",
    "SINGLEFILEWITHTAGS": "Μοναδικό αρχείο με ετικέτες",
    "NOSUBFOLDERS": "Κανένας υποφάκελος",
    "USETAGFORFOLDERS": "Χρήση ετικετών για φακέλους",
    "FLAGGED": "Με επισήμανση",
    "FLAG": "Σημαία",
    "ALLANSWERSVALID": "Μετατροπή όλων των απαντήσεων σε έγκυρες πριν από την αποθήκευση",
    "ALLOWUNVALIDANSWERS": "Να επιτρέπονται μη έγκυρες απαντήσεις",
    "LIVEANSWERS": "Ζωντανές απαντήσεις",
    "ANNOTATED": "Με σχόλια",
    "HE": "עברית",
    "AR": "عربية",
    "SMS": "Sms",
    "DISABLEALLSMS": "Απενεργοποίηση ειδοποιήσεων μέσω sms",
    "ALGORITHM": "Αλγόριθμος",
    "OPERATIONS": "Λειτουργίες",
    "RATE1": "Αξιολόγηση",
    "FIELDTYPE": "Τύπος πεδίου",
    "FIELDIF": "Αν",
    "FIELDIS": "είναι",
    "TRANSLATE": "Μετάφραση",
    "ALLPHOTOS": "Όλες οι φωτογραφίες",
    "FLAGGEDPHOTOS": "Φωτογραφίες με επισήμανση",
    "UNFLAGGEDPHOTOS": "Φωτογραφίες χωρίς επισήμανση",
    "VALIDATEDON": "",
    "CAMPAIGNHELP": "Καλώς ορίσατε στον οδηγό δημιουργίας καμπάνιας.<br\/>Ας ξεκινήσουμε με τον ορισμό του τρόπου εμφάνισης της αναζήτησης για τους χρήστες.",
    "LOCATIONSHELP": "Επιλέξτε τα καταστήματα στα οποία θέλετε να δημοσιεύσετε τις αναζητήσεις σας.\"",
    "PUBLISHHELP": "Διαλέξτε τις επιλογές που θέλετε να χρησιμοποιήσετε όταν δημοσιεύετε τις αναζητήσεις σας.",
    "WALKTHROUGH.CROWD.1.DESCRIPTION": "",
    "WALKTHROUGH.CROWD.2.DESCRIPTION": "",
    "WALKTHROUGH.CROWD.3.DESCRIPTION": "",
    "WALKTHROUGH.TEAM.1.DESCRIPTION": "",
    "WALKTHROUGH.TEAM.2.DESCRIPTION": "",
    "WALKTHROUGH.TEAM.3.DESCRIPTION": "",
    "WALKTHROUGH.SERVICE.1.DESCRIPTION": "",
    "WALKTHROUGH.SERVICE.2.DESCRIPTION": "",
    "WALKTHROUGH.SERVICE.3.DESCRIPTION": "",
    "WALKTHROUGH.ASK.1.DESCRIPTION": "",
    "WALKTHROUGH.ASK.2.DESCRIPTION": "",
    "WALKTHROUGH.ASK.3.DESCRIPTION": "",
    "TEMPLATE": "Πρότυπο",
    "TIMEFORMAT": "ΩΩ:λλ",
    "LOGINSUBTITLE": "Εισαγάγετε τα στοιχεία σας παρακάτω",
    "LOGINBASELINE1": "Βελτιώστε την επίδοση του καταστήματός σας",
    "LOGINBASELINE2": "Έλεγχος & Συμβατότητα.<br\/> Εκτέλεση εντός καταστήματος.<br\/> Επικοινωνία & Εκπαίδευση.",
    "PASSWORDENTER": "Εισαγωγή κωδικού πρόσβασης",
    "FOODRETAIL": "Λιανική πώληση τροφίμων",
    "TRAVELRETAIL": "Λιανική πώληση ταξιδιών",
    "AUTOMOTIVE": "Κλάδος αυτοκινήτων",
    "FASHIONRETAIL": "Λιανική πώληση ρούχων",
    "PETROLSTATION": "Σταθμός πώλησης καυσίμων",
    "COSMETIC": "Καλλυντικά",
    "AGENCY": "Γραφείο υπηρεσιών μάρκετινγκ",
    "RESTAURANT": "Εστιατόριο",
    "PARMACEUTICAL": "Φαρμακευτικά",
    "RETAIL": "Λιανικές πωλήσεις",
    "TRIALUSERTYPE": "Για να σας παρέχουμε την καλύτερη δυνατή εμπειρία YOOBIC, θα θέλαμε να μας πείτε σε ποια κατηγορία ταιριάζετε καλύτερα.",
    "TRIALUSERPOSITION": "Ποια είναι η τρέχουσα θέση σας στην εταιρία;",
    "TRIAL": "Δοκιμή",
    "INITIALIZED": "Έγινε προετοιμασία",
    "POSITION": "Θέση",
    "ALLOWANCE": "Επίδομα",
    "REMAINING": "Απομένει(-ουν)",
    "TRIALCREATENEWLOCATIONS": "Ας ξεκινήσουμε με τη δημιουργία του καταστήματός σας.<br\/> Κάντε κλικ στο κουμπί Δημιουργία για να προσθέσετε το κατάστημα.",
    "TRIALCREATENEWUSERS": "Τέλεια. Ας συνεχίσουμε προσκαλώντας κι άλλους χρήστες.<br\/> Κάντε κλικ στο κουμπί δημιουργίας για να προσκαλέσετε τους συναδέλφους σας.",
    "LATE": "Με καθυστέρηση",
    "MARGINDAYS": "Περιθώριο (αριθμός ημερών)",
    "DELETECONFIRM": "Θέλετε σίγουρα να διαγράψετε αυτό το στοιχείο;",
    "DONE": "Ολοκληρώθηκε",
    "GETSTARTED": "Ξεκινήστε",
    "ROLE": "Ρόλος ",
    "STOREMANAGER": "Διευθυντής καταστήματος",
    "REGIONALMANAGER": "Περιφερειακός διευθυντής",
    "HEADQUARTER": "Κεντρικά γραφεία",
    "INTRODUCTION": "Εισαγωγή",
    "TRIALINTRODUCTION": "ΕΙΣΑΓΩΓΗΔΟΚΙΜΑΣΤΙΚΟΥ",
    "SELECTIMAGE": "Επιλογή εικόνων",
    "ALLOWOPENDETAILS": "Να επιτρέπεται το άνοιγμα λεπτομερειών",
    "ALLOWSAMEUSERVALIDATION": "Επικύρωση ίδιου χρήστη",
    "EXTERNAL": "Εξωτερικό",
    "LOCKEDDATE": "Κλειδωμένο (ημερομηνία)",
    "MISSIONGROUPS": "Ομάδες που μπορούν να δουν\/ολοκληρώσουν αυτήν την αποστολή",
    "ISPRIMARYSCORE": "Είναι πρωτεύον το σκορ;",
    "VALIDFROMTOOLTIP": "Οι αποστολές θα είναι ορατές στην εφαρμογή αλλά οι χρήστες δεν θα μπορούν να τις εκκινήσουν μέχρι να φτάσει η ημερομηνία επικύρωσης.",
    "VALIDUNTILTOOLTIP": "Μετά από αυτήν την ημερομηνία οι διαθέσιμες αποστολές θα διαγραφούν αυτόματα.",
    "EDITGROUPS": "Επεξεργασία ομάδων",
    "YOOTIME.WELCOME": "",
    "YOOTIME.NOACCOUNT": "",
    "YOOTIME.SIGNUP": "",
    "YOOTIME.OVERVIEW": "",
    "YOOTIME.TIMESHEET": "",
    "YOOTIME.HISTORY": "",
    "YOOTIME.TASKTOTAL": "",
    "YOOTIME.MYTOTALS": "",
    "YOOTIME.WEEKLYTOTAL": "",
    "YOOTIME.THISPAYPERIOD": "",
    "YOOTIME.MYWORK": "",
    "YOOTIME.WEEKLYJOBCODES": "",
    "YOOTIME.PAIDTIMEOFF": "",
    "YOOTIME.TYPE": "",
    "YOOTIME.AVAILABLE": "",
    "USEOFFLINEMODE": "Λειτουργία εκτός σύνδεσης",
    "ALLPHOTOSREQUIRED": "Απαιτούνται όλες οι φωτογραφίες",
    "REPUBLISHWITHANSWERS": "Προσυμπληρωμένο με απαντήσεις",
    "DURATIONMAX": "Μέγιστη διάρκεια (δευτ.)",
    "MISSIONTYPE": "Τύπος αποστολής",
    "SATISFACTORY": "Ικανοποιητική",
    "UNSATISFACTORY": "Μη ικανοποιητική",
    "WK_TITLE_1": "Δείτε, λάβετε και ολοκληρώστε εργασίες",
    "WK_SUBTITLE_1": "Μάθετε τι έχετε να κάνετε και πότε. Στείλτε ότι έχετε κάνει.",
    "WK_TITLE_2": "Το μοίρασμα δείχνει ότι ενδιαφέρεστε",
    "WK_SUBTITLE_2": "Μοιραστείτε σχόλια και παραμείνετε ενημερωμένοι για τα νέα της εταιρίας.",
    "WK_TITLE_3": "Κάντε εύκολη την επικοινωνία",
    "WK_SUBTITLE_3": "Συνομιλήστε με οποιονδήποτε στην ομάδα. Επιπλέον λάβετε υποστήριξη από το YOOBIC.",
    "WK_TITLE_4": "Το σημείο επισημαίνεται με X ",
    "WK_SUBTITLE_4": "Ο ενσωματωμένος γεωγραφικός εντοπισμός θέσης διασφαλίζει ότι βλέπετε μόνο εργασίες που είναι κατάλληλες για εσάς. Μην ξεχνάτε να τον ενεργοποιείτε.",
    "WK_TITLE_5": "Μείνετε στην κορυφή του παιχνιδιού",
    "WK_SUBTITLE_5": "Ενεργοποιήστε τις ειδοποιήσεις για την εφαρμογή. Με αυτόν τον τρόπο θα είστε πάντα ενημερωμένος(-η).",
    "ADDPREDEFINEDTASKS": "Προσθήκη προκαθορισμένων εργασιών",
    "PDFCLASSIC": "Κλασσικό",
    "PDFPHOTOREPORT": "Αναφορά φωτογραφίας",
    "PDFAUDITEXPORTS": "Αναφορά ελέγχου",
    "UNSATISFACTORYANSWER": "Μη ικανοποιητικές απαντήσεις",
    "ACTIONPLAN": "Σχέδιο δράσης",
    "PDFCONTRACT": "Συμβόλαιο",
    "CZ": "česky",
    "TH": "ไทย",
    "TR": "Türkçe",
    "PHARMAONEPAYMENT": "Μια νέα πληρωμή ποσού {{amount}} € καταχωρήθηκε.",
    "MULTIPHOTOS": "Πολλαπλές φωτογραφίες",
    "MISSINGWORD": "Απουσιάζουν λέξεις",
    "SWIPESELECT": "Σάρωση",
    "KNOB": "Κουμπί",
    "SENTENCE": "Πρόταση",
    "CONNECT": "Σύνδεση",
    "SCHEDULED": "Προγραμματίστηκε",
    "HOUR": "Ώρα",
    "MINUTE": "Λεπτά",
    "VIDEOPLAYER": "Αναπαραγωγή βίντεο",
    "FLEX": "Flex",
    "BADGE": "Badge",
    "INSTAGRAM": "Instagram",
    "PROPERTIES": "Ιδιότητες",
    "SYNC": "Συγχρονισμός",
    "CUSTOMMODEL": "Προσαρμοσμένο μοντέλο",
    "APPEARANCE": "Εμφάνιση",
    "GAME": "Παιχνίδι",
    "FEEDTAGS": "Τροφοδοσία ετικετών",
    "MYSTORE": "Το κατάστημά μου",
    "MISSIONINFORMATION": "Πληροφορίες αποστολής",
    "MISSIONDUEDATE": "Η αποστολή πρέπει να ολοκληρωθεί πριν από",
    "MISSIONSETTINGS": "Ρυθμίσεις αποστολής",
    "MISSIONVALIDFROMTOOLTIP": "Η αποστολή να είναι ορατή μετά από",
    "MISSIONVALIDUNTILTOOLTIP": "Αρχειοθέτηση διαθέσιμη και αποστολή σε εξέλιξη μετά από",
    "VISIBILITY": "Ορατότητα",
    "WORDS": "Λέξεις",
    "DASHBOARDID": "Αναγνωριστικό του πίνακα εργαλείων",
    "INVENTORY": "Αποθεματικό",
    "TENANT": "Ένοικος",
    "TENANTS": "Ένοικοι",
    "IMPERSONATE": "Απρόσωπο",
    "COMPLETION": "Ολοκλήρωση",
    "HEADER": "Επικεφαλίδα",
    "FORMAT": "Μορφή",
    "SHARED": "Κοινή χρήση",
    "RECURRING": "Επαναλαμβανόμενο",
    "MAGICLINK": "Στείλτε μου ένα μαγικό σύνδεσμο",
    "KPIAVERAGESCORE": "Μέσος όρος σκορ",
    "6MONTHS": "6 μήνες",
    "EXPLANATIONDOCUMENT": "Έγγραφο επεξήγησης",
    "UPDATEDATES": "Ενημέρωση ημερομηνιών",
    "REPORTORDER": "Ορίστε μια τοποθεσία στην ενότητα Σύνοψη",
    "CHECKLIST": "Λίστα ελέγχου",
    "ADDNEWACTION": "Προσθήκη νέας ενέργειας",
    "PREVIOUSACTIONS": "Ενέργειες από την προηγούμενη επίσκεψη",
    "NEXTACTIONS": "Υπενθυμίσεις για τις επόμενες επισκέψεις σας",
    "ADDNEWTASK": "Προσθήκη νέας εργασίας",
    "ASKFORPHOTO": "Ζητήστε φωτογραφία",
    "ALLOWTASK": "Να επιτρέπονται εργασίες",
    "POWEREDBY": "Παρέχεται από",
    "WELCOMETO": "Καλωσήρθατε στο",
    "FORMULA": "Τύπος",
    "TAB": "Καρτέλα",
    "MISSIONPHOTONOTFOUNDERROR": "Παρακαλώ ελέγξτε όλες τις φωτογραφίες σας",
    "YEAR(S)": "Έτος (-οι)",
    "MONTH(S)": "Μήνας (-ες)",
    "WEEK(S)": "Εβδομάδα (-ες)",
    "DAY(S)": "Ημέρα (-ες)",
    "SERVICECREATED": "Δημιουργήθηκε ένα νέο αίτημα",
    "SERVICEGROUPS": "Ομαδες οι οποίες μπορούν να δούν\/ολοκληρώσουν αυτό το αίτημα",
    "REPUBLISHACTIONPLAN": "Αναδημοσίευση ενός πλάνου δράσης",
    "BG": "Болгарьска",
    "EL": "Ελληνικά",
    "SL": "Slovenščina",
    "SK": "Slovenčina",
    "PAUSE": "Παύση",
    "GAMEOVER": "Το παιχνίδι τελείωσε",
    "MEMORY-GAME-INSTRUCTIONS": "Απομνημονεύστε τα ζεύγη καρτών!",
    "HOME2": "Αρχική",
    "VIEWLESS": "Εμφάνιση λιγότερων",
    "ASSIGN": "Εκχώρηση",
    "SCHEDULE": "Πρόγραμμα",
    "TOMORROW": "Αύριο",
    "USERACTIVE": "Ενεργοί χρήστες",
    "COMPAREDTOPREVIOUSWEEK": "Σύγκριση με τις προηγούμενες 7 ημέρες",
    "MEMO": "Υπόμνημα",
    "SHARETOFEED": "Κοινή χρήση στην τροφοδοσία ειδήσεων",
    "PROVIDER": "Πάροχος",
    "RECENTS": "Πρόσφατα",
    "COMMENTEDYOURFEED": " σχολίασε την τροφοδοσία σας",
    "LIKEDYOURFEED": " του άρεσε η τροφοδοσία σας",
    "LIKEDYOURFEEDCOMMENT": "του άρεσε το σχόλιό σας",
    "REPLY": "Απάντηση",
    "BROWSE": "Αναζήτηση",
    "REMEMBERME": "Απομνημόνευση των στοιχείων μου",
    "REPUBLISH": "Επανάληψη δημοσίευσης",
    "KPICAMPAIGNSVALIDATIONPROGRESS": "Ταχύτητα επικύρωσης",
    "KPICAMPAIGNSCONFORMITYPROGRESS": "Ταχύτητα συμβατότητας",
    "KPICAMPAIGNSPROGRESS": "Ταχύτητα ολοκλήρωσης",
    "CONFORMITYPROGRESS": "Συμβατότητα",
    "CONFORMITY": "Συμβατότητα",
    "CONFORMITYRELATIVEPROGRESS": "Σχετική συμβατότητα",
    "ROLEMANAGER": "Μάνατζερ",
    "ROLEEDITOR": "Επιμελητής",
    "ROLEVIEWER": "Θεατής",
    "ROLEFIELD": "Ομάδα πεδίου",
    "ROLESTOREMANAGER": "Διευθυντής καταστήματος",
    "ROLESTORE": "Ομάδα αποθήκευσης",
    "ROLEADMIN": "Διαχειριστής",
    "PREFIX": "Πρόθεμα",
    "SOURCE": "Πηγή",
    "TARGET": "Στόχος",
    "ADVANCEDLOGIN": "Προχωρημένη σύνδεση",
    "METHOD": "Μέθοδος",
    "AUDITREPUBLISH": "Επαναφορά δεδομένων",
    "AUDITREPUBLISHWITHANSWERS": "Θέλετε να προχωρήσετε σε ανάκτηση των δεδομένων της τελευταίας αποστολής;",
    "QUERYISTOOBIG": "Το ερώτημα είναι υπερβολικά μεγάλο",
    "BUTTONS": "Πλήκτρα",
    "STEPS": "Βήματα",
    "WALKTHROUGH": {
        "CROWD": {
            "1": {
                "DESCRIPTION": ""
            },
            "2": {
                "DESCRIPTION": ""
            },
            "3": {
                "DESCRIPTION": ""
            }
        },
        "TEAM": {
            "1": {
                "DESCRIPTION": ""
            },
            "2": {
                "DESCRIPTION": ""
            },
            "3": {
                "DESCRIPTION": ""
            }
        },
        "SERVICE": {
            "1": {
                "DESCRIPTION": ""
            },
            "2": {
                "DESCRIPTION": ""
            },
            "3": {
                "DESCRIPTION": ""
            }
        },
        "ASK": {
            "1": {
                "DESCRIPTION": ""
            },
            "2": {
                "DESCRIPTION": ""
            },
            "3": {
                "DESCRIPTION": ""
            }
        }
    },
    "QUIZZ": "Κουίζ",
    "SECURITY": "Ασφάλεια",
    "QUESTIONS": "Ερωτήσεις",
    "VOTE": "Ψηφοφορία",
    "VIDEO": "Βίντεο",
    "DOCUMENT": "Έγγραφο",
    "NOTIFICATIONS": "Ειδοποιήσεις",
    "LESSON": "Μάθημα",
    "ADDTASK": "Προσθέστε εργασία",
    "BACKGROUNDPROCESS": "Απόκρυψη αναγνώρισης εικόνας από το κινητό",
    "ASSIGNSUCCESS": "Έχετε αναθέσει με επιτυχία αυτήν την αποστολή.",
    "MISSIONEMPTY": "Όλα τελείωσαν!<br\/>Έχετε πιάσει όλους τους στόχους σας.",
    "MEMOEMPTY": "Δεν υπάρχει ακόμη εργασία!",
    "REQUESTEMPTY": "Δεν υπάρχει ακόμη αίτημα!",
    "HEALTHSCORE": "Βαθμός Κατάστασης",
    "REACTIVITY": "Δραστικότητα",
    "COMPLIANCE": "Συμμόρφωση",
    "ACCURACY": "Ακρίβεια",
    "REVIEW": "Αξιολόγηση",
    "LOWEST": "Χαμηλότερο",
    "HIGHEST": "Υψηλότερο",
    "EVOLUTION": "Εξέλιξη",
    "COMPARISON": "Σύγκριση",
    "TAPTOINSERTCOMMENT": "Πατήστε οπουδήποτε για να εισαγάγετε σχόλιο",
    "MYTASKLIST": "Η λίστα εργασιών μου",
    "NEWEVENTPUBLISHED": "Η εκδήλωση δημοσιεύτηκε",
    "NEWMEMOCREATED": "Δημιουργήθηκε νέα εργασία",
    "SHAREDIN": "Κοινοποιήθηκε σε",
    "POST": "Δημοσίευση",
    "AT": "σε",
    "LASTHOUR": "Την Τελευταία Ώρα",
    "HEALTH": "Κατάσταση",
    "EDITACTION": "Επεξεργαστείτε μια ενέργεια",
    "DISCARDPHOTO": "Απόρριψη αλλαγών;",
    "AREYOUSURE": "Αν πάτε πίσω τώρα, θα χάσετε τις αλλαγές σας.",
    "KEEP": "Διατήρηση",
    "DISCARD": "Απόρριψη",
    "SCHEDULESUCCESS": "Η αποστολή σας προγραμματίστηκε με επιτυχία",
    "NEWPOST": "Νέα Δημοσίευση",
    "TASKCREATEDESCRIPTION": "Η εργασία είναι μια ενέργεια που πρέπει να ολοκληρωθεί σε μια καθορισμένη ημερομηνία που ορίσατε, από το άτομο στο οποίο αναθέτετε την εργασία.",
    "REQUESTCREATEDESCRIPTION": "Τα αιτήματα χρησιμοποιούνται για να ζητήσετε από τον διευθυντή σας κάτι για το κατάστημά σας.",
    "FEEDCREATEDESCRIPTION": "Δημοσιεύστε ένα άρθρο που θέλετε να κοινοποιήσετε στη Ροή Ειδήσεων μιας ομάδας χρηστών.",
    "EVENTCREATEDESCRIPTION": "Μια εκδήλωση θα επισυναφθεί στο ημερολόγιό σας και\/ή στο ημερολόγιο του επισκέπτη σας.",
    "CHATCREATEDESCRIPTION": "Η συζήτηση είναι ένας τρόπος επικοινωνίας με ένα ή περισσότερα μέλη των ομάδων σας.",
    "TERMSANDCONDITIONCONTENT": "Lorem ipsum ....",
    "MISSIONASSIGNDESCRIPTION": "Αναθέστε αυτήν την αποστολή σε έναν συνάδελφό σας",
    "MISSIONSCHEDULEDESCRIPTION": "Προγραμματίστε αυτήν την αποστολή και προσθέστε την στο ημερολόγιό σας",
    "MISSIONSAVING": "Υποβολή της αποστολής σας ...",
    "SERVICESAVING": "Υποβολή του αιτήματός σας ...",
    "PHOTOSPERPAGE": "Φωτογραφίες ανά σελίδα",
    "TUTOFIRSTCONNEXIONTEXTONE": "",
    "TUTOFIRSTCONNEXIONBTNONE": "",
    "TUTOFIRSTCONNEXIONTEXTTWO": "",
    "TUTOFIRSTCONNEXIONBTNTWO": "",
    "TUTOFIRSTCONNEXIONTEXTTHREE": "",
    "TUTOFIRSTCONNEXIONBTNTHREE": "",
    "TUTOFIRSTCONNEXIONTEXTFOUR": "",
    "TUTOFIRSTCONNEXIONBTNFOUR": "",
    "TUTOFIRSTCONNEXIONTEXTFIVE": "",
    "TUTOFIRSTCONNEXIONBTNFIVE": "",
    "TUTOFIRSTCONNEXIONBTNSIX": "",
    "TUTOFIRSTCONNEXIONTEXTSIX": "",
    "TUTOFIRSTCONNEXIONTEXTSEVEN": "",
    "TUTOFIRSTCONNEXIONBTNSEVEN": "",
    "TUTOSEARCHTEXT": "",
    "TUTOSEARCHBTN": "",
    "TUTOCALENDARTEXT": "",
    "TUTOCALENDARBTN": "",
    "TUTOADDTEXT": "",
    "TUTOADDBTN": "",
    "TUTONEWSFEEDTEXTONE": "",
    "TUTONEWSFEEDBTNONE": "",
    "TUTONEWSFEEDTEXTTWO": "",
    "TUTONEWSFEEDBTNTWO": "",
    "TUTOMYSTORETEXTONE": "",
    "TUTOMYSTOREBTNONE": "",
    "TUTOMYSTORETEXTTWO": "",
    "TUTOMYSTOREBTNTWO": "",
    "TUTOCHATTEXTONE": "",
    "TUTOCHATBTNONE": "",
    "TUTOCHATTEXTTWO": "",
    "TUTOCHATBTNTWO": "",
    "TUTOACTIVITYTEXT": "",
    "TUTOACTIVITYBTN": "",
    "SELECTEDUSER": "",
    "SELECTEDUSERS": "",
    "TOVALIDATE": "",
    "FAVOURITE": "",
    "UNFAVOURITE": "",
    "UNDEFINED": "",
    "RENAMEYOURLIST": "",
    "DELETEMEMOLISTCONFIRM": "",
    "MYAREA": "",
    "EDITINGCOMMENT": "",
    "OPENMISSION": "",
    "LASTVISIT": "",
    "SERVICESRECEIVED": "",
    "SERVICESRAISED": "",
    "VISITS": "",
    "VISIT": "",
    "LOCATIONINSIGHTSEXPLANATION": "",
    "LOCATIONVISITSEXPLANATION": "",
    "LOCATIONSTOREEXPLANATION": "",
    "PASTMISSIONS": "",
    "CHATWITHMANAGER": "",
    "CHATWITHOWNER": "",
    "CONTACTEMPTY": "",
    "NOTEEMPTY": "",
    "VISITCREATEDESCRIPTION": "",
    "VISITCOUNT": "",
    "MISSIONSTODOEMPTY": "",
    "REQUESTRECEIVEDEMPTY": "",
    "PASTMISSIONSEMPTY": "",
    "STORETODOEMPTY": "",
    "TOVALIDATEEMPTY": "",
    "STOREPASTMISSIONSEMPTY": "",
    "TURNOVER": "",
    "AVGBASKET": "",
    "CONVERSATIONRATE": "",
    "AVERAGE_BASKET": "",
    "CONVERSION_RATE": "",
    "MYTASKS": "",
    "MYMISSIONS": "",
    "NOEVENTTODAY": "",
    "MEMOEDITED": "",
    "TUTOACTIVITYTWOTEXT": "",
    "TUTOACTIVITYTHREETEXT": "",
    "NEWFEEDPUBLISHEDOFFLINE": "",
    "NEWEVENTPUBLISHEDOFFLINE": "",
    "NEWMEMOCREATEDOFFLINE": "",
    "SERVICESAVEDSUCCESSOFFLINE": "",
    "UNBOOKSERVICECONFIRM": "",
    "SHOWDETAILS": "",
    "TUTOMYSTORETEXTTHREE": "",
    "POLLSAVING": "",
    "POLLSAVINGOFFLINE": "",
    "MISSIONSAVINGOFFLINE": "",
    "SERVICESAVINGOFFLINE": "",
    "SYNCINGMISSIONS": ""
}